[
    {
        "allowed_username": [
            "redfox"
        ],
        "proxies": [
            {
                "name": " RedFox 34"
            },
            {
                "name": " RedFox 35"
            },
            {
                "name": " RedFox 36"
            },
            {
                "name": " RedFox 37"
            },
            {
                "name": " RedFox 38"
            },
            {
                "name": " RedFox 39"
            }
        ]
    }
]