[
    {
        "allowed_ips": [
            "192.168.1.10",
            "192.168.1.20",
            "10.10.10.15"
        ],
        "proxies": [
            {
                "name": "🇸🇬 SG Proxy 1"
            },
            {
                "name": "🇺🇸 US Proxy Alpha"
            },
            {
                "name": "🛰️ SpaceNet"
            }
        ]
    },
    {
        "allowed_ips": [
            "103.178.186.146",
            "103.245.96.21",
            "203.76.148.154"
        ],
        "proxies": [
            {
                "name": "🦊 RedFox 50"
            },
            {
                "name": "🦊 RedFox 12"
            }
        ]
    },
    {
        "allowed_ips": [
            "103.245.96.20",
            "103.108.60.35"
        ],
        "proxies": [
            {
                "name": "🦊 RedFox 6"
            }
        ]
    }
]